{
  "name": "thirdweek",
  "type": "C51",
  "dependenceList": [],
  "srcDirs": [
    "src"
  ],
  "virtualFolder": {
    "name": "<virtual_root>",
    "files": [],
    "folders": []
  },
  "outDir": "build",
  "deviceName": null,
  "packDir": null,
  "miscInfo": {
    "uid": "0fe94dc84dba09f37d009483277b5559"
  },
  "targets": {
    "Debug": {
      "excludeList": [],
      "toolchain": "Keil_C51",
      "compileConfig": {
        "options": "null"
      },
      "uploader": "Custom",
      "uploadConfig": {
        "bin": "",
        "commandLine": "python ./tools/stcflash.py -p ${port} \"${programFile}\"",
        "eraseChipCommand": ""
      },
      "uploadConfigMap": {
        "Custom": {
          "bin": "",
          "commandLine": "python ./tools/stcflash.py -p ${port} \"${programFile}\"",
          "eraseChipCommand": ""
        },
        "stcgal": {
          "bin": "",
          "eepromImgPath": "null",
          "extraOptions": "",
          "options": ".eide/stc.flash.json"
        }
      },
      "custom_dep": {
        "name": "default",
        "incList": [
          "inc",
          "../../../../../Program Files/keil5/C51/INC/Atmel",
          "../../../../../Program Files/keil5/C51/INC"
        ],
        "libList": [
          "../../../../../Program Files/keil5/C51/LIB",
          "../../../../../Program Files/keil5/C51/INC/Atmel"
        ],
        "sourceDirList": [],
        "defineList": []
      }
    }
  },
  "version": "3.3"
}